[{
    "Content": {
        "Md": "---\nlayout: post\ntitle: The Buffalo Jerky Shankle Tongue Beef Ribs Conspiracy\nauthor: Mrs. Bacon\ndate: 2020-02-02\ntags:\n    - Hamburger\n    - Drumstick\n---\n\nBacon ipsum dolor amet short loin pancetta ham hock hamburger bresaola andouille filet mignon alcatra spare ribs, buffalo pastrami biltong. Doner kevin ribeye, rump ball tip sirloin pig strip steak bresaola sausage shank biltong alcatra leberkas pork chop. Flank pork belly fatback tail meatball. Leberkas corned beef landjaeger pork kevin burgdoggen. Meatball ribeye picanha short loin, frankfurter short ribs bacon biltong fatback shoulder doner porchetta drumstick pork belly. Capicola pastrami salami sirloin cupim short loin doner landjaeger drumstick chuck. Cow shankle pork belly bresaola.\n",
        "HTML": "{\"\u003cp\u003eBacon ipsum dolor amet short loin pancetta ham hock hamburger bresaola andouille filet mignon alcatra spare ribs, buffalo pastrami biltong. Doner kevin ribeye, rump ball tip sirloin pig strip steak bresaola sausage shank biltong alcatra leberkas pork chop. Flank pork belly fatback tail meatball. Leberkas corned beef landjaeger pork kevin burgdoggen. Meatball ribeye picanha short loin, frankfurter short ribs bacon biltong fatback shoulder doner porchetta drumstick pork belly. Capicola pastrami salami sirloin cupim short loin doner landjaeger drumstick chuck. Cow shankle pork belly bresaola.\u003c/p\u003e\\n\" '\\x00' '\\x00'}"
    },
    "MetaData": {
        "author": "Mrs. Bacon",
        "date": "2020-02-02",
        "layout": "post",
        "tags": ["Hamburger", "Drumstick"],
        "title": "The Buffalo Jerky Shankle Tongue Beef Ribs Conspiracy"
    },
    "URL": "/bacon.md"
}, {
    "Content": {
        "Md": "---\nlayout: post\ntitle: Abra Cadaver\nauthor: The Brainteaser\ndate: 2020-03-03\ntags:\n    - Brain\n    - Milkshake\n---\n\nZombie ipsum reversus ab viral inferno, nam rick grimes malum cerebro. De carne lumbering animata corpora quaeritis. Summus brains sit​​, morbo vel maleficia? De apocalypsi gorger omero undead survivor dictum mauris. Hi mindless mortuis soulless creaturas, imo evil stalking monstra adventus resi dentevil vultus comedat cerebella viventium. Qui animated corpse, cricket bat max brucks terribilem incessu zomby.\n",
        "HTML": "{\"\u003cp\u003eZombie ipsum reversus ab viral inferno, nam rick grimes malum cerebro. De carne lumbering animata corpora quaeritis. Summus brains sit\\u200b\\u200b, morbo vel maleficia? De apocalypsi gorger omero undead survivor dictum mauris. Hi mindless mortuis soulless creaturas, imo evil stalking monstra adventus resi dentevil vultus comedat cerebella viventium. Qui animated corpse, cricket bat max brucks terribilem incessu zomby.\u003c/p\u003e\\n\" '\\x00' '\\x00'}"
    },
    "MetaData": {
        "author": "The Brainteaser",
        "date": "2020-03-03",
        "layout": "post",
        "tags": ["Brain", "Milkshake"],
        "title": "Abra Cadaver"
    },
    "URL": "/brains.md"
}, {
    "Content": {
        "Md": "---\nlayout: post\ntitle: Prow Scuttle Parrel Provost\nauthor: Jack S.\ndate: 2020-12-12\ntags:\n    - Corsair\n    - Grog\n    - Rum\n    - Milkshake\n---\n\nSail ho shrouds spirits boom mizzenmast yardarm. Pinnace holystone mizzenmast quarter crow's nest nipperkin grog yardarm hempen halter furl. Swab barque interloper chantey doubloon starboard grog black jack gangway rutters.\n\nDeadlights jack lad schooner scallywag dance the hempen jig carouser broadside cable strike colors. Bring a spring upon her cable holystone blow the man down spanker Shiver me timbers to go on account lookout wherry doubloon chase. Belay yo-ho-ho keelhaul squiffy black spot yardarm spyglass sheet transom heave to.\n\nTrysail Sail ho Corsair red ensign hulk smartly boom jib rum gangway. Case shot Shiver me timbers gangplank crack Jennys tea cup ballast Blimey lee snow crow's nest rutters. Fluke jib scourge of the seven seas boatswain schooner gaff booty Jack Tar transom spirits.\n",
        "HTML": "{\"\u003cp\u003eSail ho shrouds spirits boom mizzenmast yardarm. Pinnace holystone mizzenmast quarter crow's nest nipperkin grog yardarm hempen halter furl. Swab barque interloper chantey doubloon starboard grog black jack gangway rutters.\u003c/p\u003e\\n\u003cp\u003eDeadlights jack lad schooner scallywag dance the hempen jig carouser broadside cable strike colors. Bring a spring upon her cable holystone blow the man down spanker Shiver me timbers to go on account lookout wherry doubloon chase. Belay yo-ho-ho keelhaul squiffy black spot yardarm spyglass sheet transom heave to.\u003c/p\u003e\\n\u003cp\u003eTrysail Sail ho Corsair red ensign hulk smartly boom jib rum gangway. Case shot Shiver me timbers gangplank crack Jennys tea cup ballast Blimey lee snow crow's nest rutters. Fluke jib scourge of the seven seas boatswain schooner gaff booty Jack Tar transom spirits.\u003c/p\u003e\\n\" '\\x00' '\\x00'}"
    },
    "MetaData": {
        "author": "Jack S.",
        "date": "2020-12-12",
        "layout": "post",
        "tags": ["Corsair", "Grog", "Rum", "Milkshake"],
        "title": "Prow Scuttle Parrel Provost"
    },
    "URL": "/jack.md"
}, {
    "Content": {
        "Md": "---\nlayout: post\ntitle: Marvin, what do you make of all of this?\nauthor: Samuel L.\ndate: 2020-01-01\ntags:\n    - Milkshake\n    - Laundry\n    - Zed\n---\n\nYou think water moves fast? You should see ice. It moves like it has a mind. Like it knows it killed the world once and got a taste for murder. After the avalanche, it took us a week to climb out. Now, I don't know exactly when we turned on each other, but I know that seven of us survived the slide... and only five made it out. Now we took an oath, that I'm breaking now. We said we'd say it was the snow that killed the other two, but it wasn't. Nature is lethal but it doesn't hold a candle to man.\n",
        "HTML": "{\"\u003cp\u003eYou think water moves fast? You should see ice. It moves like it has a mind. Like it knows it killed the world once and got a taste for murder. After the avalanche, it took us a week to climb out. Now, I don't know exactly when we turned on each other, but I know that seven of us survived the slide... and only five made it out. Now we took an oath, that I'm breaking now. We said we'd say it was the snow that killed the other two, but it wasn't. Nature is lethal but it doesn't hold a candle to man.\u003c/p\u003e\\n\" '\\x00' '\\x00'}"
    },
    "MetaData": {
        "author": "Samuel L.",
        "date": "2020-01-01",
        "layout": "post",
        "tags": ["Milkshake", "Laundry", "Zed"],
        "title": "Marvin, what do you make of all of this?"
    },
    "URL": "/samuel.md"
}]
